odoo8_addon_sale_service_fleet-8.0.1.0.0.99.dev23-py3.8-nspkg.pth
odoo_addons/sale_service_fleet/README.rst
odoo_addons/sale_service_fleet/__init__.py
odoo_addons/sale_service_fleet/__openerp__.py
odoo_addons/sale_service_fleet/i18n/ca.po
odoo_addons/sale_service_fleet/i18n/de.po
odoo_addons/sale_service_fleet/i18n/el_GR.po
odoo_addons/sale_service_fleet/i18n/es.po
odoo_addons/sale_service_fleet/i18n/es_CR.po
odoo_addons/sale_service_fleet/i18n/es_ES.po
odoo_addons/sale_service_fleet/i18n/es_MX.po
odoo_addons/sale_service_fleet/i18n/es_VE.po
odoo_addons/sale_service_fleet/i18n/fi.po
odoo_addons/sale_service_fleet/i18n/fr.po
odoo_addons/sale_service_fleet/i18n/gl.po
odoo_addons/sale_service_fleet/i18n/hr.po
odoo_addons/sale_service_fleet/i18n/hr_HR.po
odoo_addons/sale_service_fleet/i18n/hu.po
odoo_addons/sale_service_fleet/i18n/it.po
odoo_addons/sale_service_fleet/i18n/lt.po
odoo_addons/sale_service_fleet/i18n/lv.po
odoo_addons/sale_service_fleet/i18n/mk.po
odoo_addons/sale_service_fleet/i18n/mn.po
odoo_addons/sale_service_fleet/i18n/nl.po
odoo_addons/sale_service_fleet/i18n/nl_NL.po
odoo_addons/sale_service_fleet/i18n/pt.po
odoo_addons/sale_service_fleet/i18n/pt_BR.po
odoo_addons/sale_service_fleet/i18n/pt_PT.po
odoo_addons/sale_service_fleet/i18n/ro.po
odoo_addons/sale_service_fleet/i18n/sale_service_fleet.pot
odoo_addons/sale_service_fleet/i18n/sk.po
odoo_addons/sale_service_fleet/i18n/sk_SK.po
odoo_addons/sale_service_fleet/i18n/sl.po
odoo_addons/sale_service_fleet/i18n/sv.po
odoo_addons/sale_service_fleet/i18n/tr.po
odoo_addons/sale_service_fleet/i18n/tr_TR.po
odoo_addons/sale_service_fleet/i18n/uk.po
odoo_addons/sale_service_fleet/i18n/zh_CN.po
odoo_addons/sale_service_fleet/models/__init__.py
odoo_addons/sale_service_fleet/models/analytic.py
odoo_addons/sale_service_fleet/models/fleet.py
odoo_addons/sale_service_fleet/models/project.py
odoo_addons/sale_service_fleet/models/sale.py
odoo_addons/sale_service_fleet/models/sale_service.py
odoo8_addon_sale_service_fleet-8.0.1.0.0.99.dev23.dist-info/METADATA
odoo8_addon_sale_service_fleet-8.0.1.0.0.99.dev23.dist-info/WHEEL
odoo8_addon_sale_service_fleet-8.0.1.0.0.99.dev23.dist-info/namespace_packages.txt
odoo8_addon_sale_service_fleet-8.0.1.0.0.99.dev23.dist-info/top_level.txt
odoo8_addon_sale_service_fleet-8.0.1.0.0.99.dev23.dist-info/RECORD
